textual_qrcode/__init__.py
textual_qrcode/__main__.py
textual_qrcode/py.typed
textual_qrcode/qrcode.py
textual_qrcode-0.2.0.dist-info/LICENSE
textual_qrcode-0.2.0.dist-info/METADATA
textual_qrcode-0.2.0.dist-info/WHEEL
textual_qrcode-0.2.0.dist-info/top_level.txt
textual_qrcode-0.2.0.dist-info/RECORD
